{"commitInfo":{"timestamp":1764868482086,"operation":"WRITE","operationParameters":{"mode":"Overwrite","partitionBy":"[]"},"readVersion":62,"isolationLevel":"Serializable","isBlindAppend":false,"operationMetrics":{"numFiles":"1","numOutputRows":"5","numOutputBytes":"1720"},"engineInfo":"Apache-Spark/3.4.1 Delta-Lake/2.4.0","txnId":"f75d0302-801a-4a2c-ac76-1664e03f2433"}}
{"add":{"path":"part-00000-5d8bc3a9-501d-4307-b7e7-32a9e60df516-c000.snappy.parquet","partitionValues":{},"size":1720,"modificationTime":1764868481856,"dataChange":true,"stats":"{\"numRecords\":5,\"minValues\":{\"symbol\":\"AAPL\",\"avg_price\":132.5025,\"total_volume\":57843,\"avg_volatility\":1.6366666666666667,\"pct_upward\":33.33333333333333},\"maxValues\":{\"symbol\":\"TSLA\",\"avg_price\":3386.116666666667,\"total_volume\":262125,\"avg_volatility\":2.822857142857143,\"pct_upward\":75.0},\"nullCount\":{\"symbol\":0,\"avg_price\":0,\"total_volume\":0,\"avg_volatility\":0,\"pct_upward\":0}}"}}
{"remove":{"path":"part-00000-adf50d77-05c5-42c9-8269-41b3ba6c5827-c000.snappy.parquet","deletionTimestamp":1764868482086,"dataChange":true,"extendedFileMetadata":true,"partitionValues":{},"size":1695}}
