{"commitInfo":{"timestamp":1764888577336,"operation":"WRITE","operationParameters":{"mode":"Append","partitionBy":"[]"},"readVersion":120,"isolationLevel":"Serializable","isBlindAppend":true,"operationMetrics":{"numFiles":"1","numOutputRows":"40","numOutputBytes":"4702"},"engineInfo":"Apache-Spark/3.4.1 Delta-Lake/2.4.0","txnId":"1fb67d45-da08-4e27-8769-ac53d84dc222"}}
{"add":{"path":"part-00000-8af115f9-a27d-45cd-a821-91663b9d4e86-c000.snappy.parquet","partitionValues":{},"size":4702,"modificationTime":1764888577212,"dataChange":true,"stats":"{\"numRecords\":40,\"minValues\":{\"timestamp\":\"2025-12-04T22:48:40.821Z\",\"symbol\":\"AAPL\",\"price\":130.14,\"volume\":3426,\"rsi\":20.12,\"macd\":-1.96,\"volatility\":0.55,\"price_change\":-2.89,\"price_direction\":0,\"volume_change\":-964},\"maxValues\":{\"timestamp\":\"2025-12-04T22:49:19.888Z\",\"symbol\":\"TSLA\",\"price\":3380.99,\"volume\":49887,\"rsi\":79.63,\"macd\":1.98,\"volatility\":4.96,\"price_change\":2.95,\"price_direction\":1,\"volume_change\":995},\"nullCount\":{\"timestamp\":0,\"symbol\":0,\"price\":0,\"volume\":0,\"rsi\":0,\"macd\":0,\"volatility\":0,\"price_change\":0,\"price_direction\":0,\"volume_change\":0}}"}}
